gerardo/__init__.py
gerardo/__version__.py
gerardo/example.py
gerardo/psql_insert.py
gerardo-0.1.1.dist-info/LICENSE
gerardo-0.1.1.dist-info/METADATA
gerardo-0.1.1.dist-info/WHEEL
gerardo-0.1.1.dist-info/top_level.txt
gerardo-0.1.1.dist-info/RECORD
